mava/__init__.py
mava/constants.py
mava/fields.py
mava/models.py
mava/utils.py
mava/validators.py
mava-0.1.3.dist-info/LICENSE
mava-0.1.3.dist-info/WHEEL
mava-0.1.3.dist-info/METADATA
mava-0.1.3.dist-info/RECORD
